odoo9_addon_partner_helper-9.0.0.1.0-py2.7-nspkg.pth
odoo9_addon_partner_helper-9.0.0.1.0.dist-info/DESCRIPTION.rst
odoo9_addon_partner_helper-9.0.0.1.0.dist-info/METADATA
odoo9_addon_partner_helper-9.0.0.1.0.dist-info/RECORD
odoo9_addon_partner_helper-9.0.0.1.0.dist-info/WHEEL
odoo9_addon_partner_helper-9.0.0.1.0.dist-info/metadata.json
odoo9_addon_partner_helper-9.0.0.1.0.dist-info/namespace_packages.txt
odoo9_addon_partner_helper-9.0.0.1.0.dist-info/top_level.txt
odoo_addons/partner_helper/__init__.py
odoo_addons/partner_helper/__openerp__.py
odoo_addons/partner_helper/partner.py
odoo_addons/partner_helper/i18n/es.po
odoo_addons/partner_helper/i18n/nl.po
odoo_addons/partner_helper/i18n/pt_BR.po
odoo_addons/partner_helper/i18n/sl.po
odoo_addons/partner_helper/static/description/icon.png
